beercraft/__init__.py
beercraft/event.py
beercraft/helpers.py
beercraft/hub.py
beercraft/types.py
beercraft/util.py
beercraft-0.1.3a0.dist-info/WHEEL
beercraft-0.1.3a0.dist-info/METADATA
beercraft-0.1.3a0.dist-info/RECORD
