Metadata-Version: 2.1
Name: beercraft
Version: 0.1.3a0
Summary: A pub/sub library.
License: BSD-4-Clause
Author: Mark Gemmill
Author-email: gitlab@markgemmill.com
Requires-Python: >=3.6,<4.0
Classifier: License :: Other/Proprietary License
Classifier: Programming Language :: Python :: 3
Classifier: Programming Language :: Python :: 3.6
Classifier: Programming Language :: Python :: 3.7
Classifier: Programming Language :: Python :: 3.8
